{
  "run_type": "pilot",
  "prefectures": [
    {
      "code": "01",
      "slug": "hokkaido",
      "name": "北海道"
    },
    {
      "code": "02",
      "slug": "aomori",
      "name": "青森県"
    },
    {
      "code": "03",
      "slug": "iwate",
      "name": "岩手県"
    },
    {
      "code": "04",
      "slug": "miyagi",
      "name": "宮城県"
    },
    {
      "code": "05",
      "slug": "akita",
      "name": "秋田県"
    },
    {
      "code": "06",
      "slug": "yamagata",
      "name": "山形県"
    },
    {
      "code": "07",
      "slug": "fukushima",
      "name": "福島県"
    },
    {
      "code": "08",
      "slug": "ibaraki",
      "name": "茨城県"
    },
    {
      "code": "09",
      "slug": "tochigi",
      "name": "栃木県"
    },
    {
      "code": "10",
      "slug": "gunma",
      "name": "群馬県"
    },
    {
      "code": "11",
      "slug": "saitama",
      "name": "埼玉県"
    },
    {
      "code": "12",
      "slug": "chiba",
      "name": "千葉県"
    },
    {
      "code": "13",
      "slug": "tokyo",
      "name": "東京都"
    },
    {
      "code": "14",
      "slug": "kanagawa",
      "name": "神奈川県"
    },
    {
      "code": "15",
      "slug": "niigata",
      "name": "新潟県"
    },
    {
      "code": "16",
      "slug": "toyama",
      "name": "富山県"
    },
    {
      "code": "17",
      "slug": "ishikawa",
      "name": "石川県"
    },
    {
      "code": "18",
      "slug": "fukui",
      "name": "福井県"
    },
    {
      "code": "19",
      "slug": "yamanashi",
      "name": "山梨県"
    },
    {
      "code": "20",
      "slug": "nagano",
      "name": "長野県"
    },
    {
      "code": "21",
      "slug": "gifu",
      "name": "岐阜県"
    },
    {
      "code": "22",
      "slug": "shizuoka",
      "name": "静岡県"
    },
    {
      "code": "23",
      "slug": "aichi",
      "name": "愛知県"
    },
    {
      "code": "24",
      "slug": "mie",
      "name": "三重県"
    },
    {
      "code": "25",
      "slug": "shiga",
      "name": "滋賀県"
    },
    {
      "code": "26",
      "slug": "kyoto",
      "name": "京都府"
    },
    {
      "code": "27",
      "slug": "osaka",
      "name": "大阪府"
    },
    {
      "code": "28",
      "slug": "hyogo",
      "name": "兵庫県"
    },
    {
      "code": "29",
      "slug": "nara",
      "name": "奈良県"
    },
    {
      "code": "30",
      "slug": "wakayama",
      "name": "和歌山県"
    },
    {
      "code": "31",
      "slug": "tottori",
      "name": "鳥取県"
    },
    {
      "code": "32",
      "slug": "shimane",
      "name": "島根県"
    },
    {
      "code": "33",
      "slug": "okayama",
      "name": "岡山県"
    },
    {
      "code": "34",
      "slug": "hiroshima",
      "name": "広島県"
    },
    {
      "code": "35",
      "slug": "yamaguchi",
      "name": "山口県"
    },
    {
      "code": "36",
      "slug": "tokushima",
      "name": "徳島県"
    },
    {
      "code": "37",
      "slug": "kagawa",
      "name": "香川県"
    },
    {
      "code": "38",
      "slug": "ehime",
      "name": "愛媛県"
    },
    {
      "code": "39",
      "slug": "kochi",
      "name": "高知県"
    },
    {
      "code": "40",
      "slug": "fukuoka",
      "name": "福岡県"
    },
    {
      "code": "41",
      "slug": "saga",
      "name": "佐賀県"
    },
    {
      "code": "42",
      "slug": "nagasaki",
      "name": "長崎県"
    },
    {
      "code": "43",
      "slug": "kumamoto",
      "name": "熊本県"
    },
    {
      "code": "44",
      "slug": "oita",
      "name": "大分県"
    },
    {
      "code": "45",
      "slug": "miyazaki",
      "name": "宮崎県"
    },
    {
      "code": "46",
      "slug": "kagoshima",
      "name": "鹿児島県"
    },
    {
      "code": "47",
      "slug": "okinawa",
      "name": "沖縄県"
    }
  ],
  "started_at": "2026-04-25T22:43:04.162Z",
  "finished_at": "2026-04-26T06:57:13.318Z",
  "elapsed_seconds": 29649,
  "aborted": false,
  "abort_reason": null,
  "http": {
    "success": 79129,
    "fivexx": 235,
    "fourxx": 19809,
    "network_errors": 419
  }
}