{
  "id": "4c441274b22d",
  "confidence": "likely",
  "match_reasons": [
    "distance 99m",
    "name similarity 0.80 (likely)"
  ],
  "candidates": [
    {
      "source": "osm",
      "source_id": "node/5008989135",
      "source_url": "https://www.openstreetmap.org/node/5008989135",
      "name": "高砂屋 本館",
      "name_en": "Takasagoya Honkan",
      "name_zh": null,
      "name_ko": null,
      "coordinates": {
        "lat": 38.3115305,
        "lng": 140.4346786
      },
      "phone": "+81 23 695 2121",
      "street": null,
      "postal_code": null,
      "website": null,
      "type": "hotel",
      "prefecture_code": "06",
      "raw": {
        "osm_id": "node/5008989135",
        "osm_url": "https://www.openstreetmap.org/node/5008989135",
        "type": "hotel",
        "name": "高砂屋 本館",
        "name_en": "Takasagoya Honkan",
        "name_zh": null,
        "name_ko": null,
        "coordinates": {
          "lat": 38.3115305,
          "lng": 140.4346786
        },
        "postal_code": null,
        "full_address": null,
        "city": null,
        "street": null,
        "phone": "+81 23 695 2121",
        "website": null,
        "stars": null,
        "raw_tags": {
          "check_date": "2025-07-06",
          "name": "高砂屋 本館",
          "name:en": "Takasagoya Honkan",
          "name:ja": "高砂屋 本館",
          "phone": "+81 23 695 2121",
          "tourism": "hotel"
        }
      }
    },
    {
      "source": "osm",
      "source_id": "node/5009017629",
      "source_url": "https://www.openstreetmap.org/node/5009017629",
      "name": "高砂屋別館",
      "name_en": "Takasagoya Bekkan",
      "name_zh": null,
      "name_ko": null,
      "coordinates": {
        "lat": 38.310716,
        "lng": 140.4351389
      },
      "phone": "+81 23 695 2038",
      "street": null,
      "postal_code": null,
      "website": null,
      "type": "hotel",
      "prefecture_code": "06",
      "raw": {
        "osm_id": "node/5009017629",
        "osm_url": "https://www.openstreetmap.org/node/5009017629",
        "type": "hotel",
        "name": "高砂屋別館",
        "name_en": "Takasagoya Bekkan",
        "name_zh": null,
        "name_ko": null,
        "coordinates": {
          "lat": 38.310716,
          "lng": 140.4351389
        },
        "postal_code": null,
        "full_address": null,
        "city": null,
        "street": null,
        "phone": "+81 23 695 2038",
        "website": null,
        "stars": null,
        "raw_tags": {
          "name": "高砂屋別館",
          "name:en": "Takasagoya Bekkan",
          "phone": "+81 23 695 2038",
          "tourism": "hotel"
        }
      }
    }
  ]
}