{
  "id": "9f8b595887e5",
  "confidence": "likely",
  "match_reasons": [
    "distance 69m",
    "name similarity 0.67 (likely)"
  ],
  "candidates": [
    {
      "source": "osm",
      "source_id": "node/368718291",
      "source_url": "https://www.openstreetmap.org/node/368718291",
      "name": "엠모텔",
      "name_en": "Em Motel",
      "name_zh": null,
      "name_ko": "엠모텔",
      "coordinates": {
        "lat": 36.012058,
        "lng": 129.347365
      },
      "phone": null,
      "street": null,
      "postal_code": null,
      "website": null,
      "type": "motel",
      "prefecture_code": null,
      "raw": {
        "osm_id": "node/368718291",
        "osm_url": "https://www.openstreetmap.org/node/368718291",
        "type": "motel",
        "name": "엠모텔",
        "name_en": "Em Motel",
        "name_zh": null,
        "name_ko": "엠모텔",
        "coordinates": {
          "lat": 36.012058,
          "lng": 129.347365
        },
        "postal_code": null,
        "full_address": null,
        "city": null,
        "street": null,
        "phone": null,
        "website": null,
        "stars": null,
        "raw_tags": {
          "name": "엠모텔",
          "name:en": "Em Motel",
          "name:ko": "엠모텔",
          "name:ko-Latn": "Emmotel",
          "tourism": "motel"
        }
      }
    },
    {
      "source": "osm",
      "source_id": "node/368718322",
      "source_url": "https://www.openstreetmap.org/node/368718322",
      "name": "선모텔",
      "name_en": "Seon Motel",
      "name_zh": null,
      "name_ko": "선모텔",
      "coordinates": {
        "lat": 36.012284,
        "lng": 129.348079
      },
      "phone": null,
      "street": null,
      "postal_code": null,
      "website": null,
      "type": "motel",
      "prefecture_code": null,
      "raw": {
        "osm_id": "node/368718322",
        "osm_url": "https://www.openstreetmap.org/node/368718322",
        "type": "motel",
        "name": "선모텔",
        "name_en": "Seon Motel",
        "name_zh": null,
        "name_ko": "선모텔",
        "coordinates": {
          "lat": 36.012284,
          "lng": 129.348079
        },
        "postal_code": null,
        "full_address": null,
        "city": null,
        "street": null,
        "phone": null,
        "website": null,
        "stars": null,
        "raw_tags": {
          "name": "선모텔",
          "name:en": "Seon Motel",
          "name:ko": "선모텔",
          "name:ko-Latn": "Seonmotel",
          "tourism": "motel"
        }
      }
    }
  ]
}